simple_sharepoint/__init__.py
simple_sharepoint/__main__.py
simple_sharepoint/client.py
simple_sharepoint/utils.py
simple_sharepoint-0.1.6.dist-info/METADATA
simple_sharepoint-0.1.6.dist-info/WHEEL
simple_sharepoint-0.1.6.dist-info/entry_points.txt
simple_sharepoint-0.1.6.dist-info/top_level.txt
simple_sharepoint-0.1.6.dist-info/RECORD
