Metadata-Version: 2.4
Name: simple-sharepoint
Version: 0.1.6
Summary: Simple way to handle sharepoint with python
Author: Wellbia.com Co.,Ltd.
Author-email: opensource@wellbia.com
Classifier: License :: OSI Approved :: MIT License
Classifier: Programming Language :: Python :: 3.6
Classifier: Programming Language :: Python :: 3.7
Classifier: Programming Language :: Python :: 3.8
Classifier: Programming Language :: Python :: 3.9
Requires-Dist: Office365-REST-Python-Client
Dynamic: author
Dynamic: author-email
Dynamic: classifier
Dynamic: description
Dynamic: description-content-type
Dynamic: requires-dist
Dynamic: summary
